gender_guess/__init__.py
gender_guess/core.py
gender_guess/evaluation.py
gender_guess/gender_api.py
gender_guess/gender_solvers.py
gender_guess/loaders.py
gender_guess/processor.py
gender_guess/test_gender_pipeline.py
gender_guess/genderComputer/__init__.py
gender_guess/genderComputer/dictUtils.py
gender_guess/genderComputer/filters.py
gender_guess/genderComputer/genderComputer.py
gender_guess/genderComputer/genderc_python.py
gender_guess/genderComputer/nameUtils.py
gender_guess/nameLists/AfghanistanFemaleUTF8.csv
gender_guess/nameLists/AfghanistanMaleUTF8.csv
gender_guess/nameLists/AlbaniaFemaleUTF8.csv
gender_guess/nameLists/AlbaniaMaleUTF8.csv
gender_guess/nameLists/AustraliaFemaleUTF8.csv
gender_guess/nameLists/AustraliaMaleUTF8.csv
gender_guess/nameLists/BelgiumFemaleUTF8.csv
gender_guess/nameLists/BelgiumMaleUTF8.csv
gender_guess/nameLists/BrazilFemaleUTF8.csv
gender_guess/nameLists/BrazilMaleUTF8.csv
gender_guess/nameLists/BrusselsFemaleUTF8.csv
gender_guess/nameLists/BrusselsMaleUTF8.csv
gender_guess/nameLists/CanadaFemaleUTF8.csv
gender_guess/nameLists/CanadaMaleUTF8.csv
gender_guess/nameLists/CzechFemaleUTF8.csv
gender_guess/nameLists/CzechMaleUTF8.csv
gender_guess/nameLists/FinlandFemaleUTF8.csv
gender_guess/nameLists/FinlandMaleUTF8.csv
gender_guess/nameLists/FlandersFemaleUTF8.csv
gender_guess/nameLists/FlandersMaleUTF8.csv
gender_guess/nameLists/FrisiaFemaleUTF8.csv
gender_guess/nameLists/FrisiaMaleUTF8.csv
gender_guess/nameLists/GermanyFemaleUTF8.csv
gender_guess/nameLists/GermanyMaleUTF8.csv
gender_guess/nameLists/GreeceFemaleUTF8.csv
gender_guess/nameLists/GreeceMaleUTF8.csv
gender_guess/nameLists/HungaryFemaleUTF8.csv
gender_guess/nameLists/HungaryMaleUTF8.csv
gender_guess/nameLists/IndiaFemaleUTF8.csv
gender_guess/nameLists/IndiaLastNames.csv
gender_guess/nameLists/IndiaMaleUTF8.csv
gender_guess/nameLists/IranFemaleUTF8.csv
gender_guess/nameLists/IranMaleUTF8.csv
gender_guess/nameLists/IrelandFemaleUTF8.csv
tml_gender_guess-0.1.11.dist-info/METADATA
tml_gender_guess-0.1.11.dist-info/WHEEL
tml_gender_guess-0.1.11.dist-info/top_level.txt
tml_gender_guess-0.1.11.dist-info/RECORD
