Metadata-Version: 2.4
Name: tml_gender_guess
Version: 0.1.11
Summary: Gender classification pipeline based on names
Author: José Ángel Morell
Requires-Dist: pandas>=2.2.3
Requires-Dist: tqdm>=4.67.1
Requires-Dist: scikit-learn>=1.6.1
Requires-Dist: torch>=2.6.0
Requires-Dist: transformers>=4.51.1
Requires-Dist: uvicorn>=0.34.1
Requires-Dist: nltk>=3.9.1
Requires-Dist: requests>=2.32.3
Requires-Dist: regex>=2024.11.6
Requires-Dist: Unidecode>=1.3.2
Requires-Dist: nameparser>=1.0.6
Requires-Dist: typing-inspection>=0.4.0
Requires-Dist: wordsegment>=1.3.1
Requires-Dist: wordninja>=2.0.0
Dynamic: author
Dynamic: requires-dist
Dynamic: summary
